Bs_Extractor/__init__.py
Bs_Extractor/constants.py
Bs_Extractor/data_extractor.py
Bs_Extractor/data_extractor2.py
Bs_Extractor/functions.py
Bs_Extractor-1.3.5.dist-info/LICENSE
Bs_Extractor-1.3.5.dist-info/METADATA
Bs_Extractor-1.3.5.dist-info/WHEEL
Bs_Extractor-1.3.5.dist-info/top_level.txt
Bs_Extractor-1.3.5.dist-info/RECORD
